{"id_query": "1005407", "total": 26330, "total_current": 100, "max_score": 113.45933, "origin_question": "Ban oi cho minh hoi ben minh khi mua iphone thanh toan bang the mastercad cua ngan hang nao thi duoc nhi ?", "hits": [{"score": 113.45933, "id": "1005407", "field_search": "question", "question": "Ban oi cho minh hoi ben minh khi mua iphone thanh toan bang the mastercad cua ngan hang nao thi duoc nhi ?", "answer": "_", "relate_q_q": 0}, {"score": 43.121338, "id": "1015097", "field_search": "question", "question": "Chao moi nguoi, cho minh hoi: minh co the su dung the VISA cua nuoc ngoai de thanh toan online tai website cua thegioididong duoc khong?", "answer": "_", "relate_q_q": 0}, {"score": 37.843548, "id": "813046", "field_search": "question", "question": "P oi cho minh hoi tai sao minh goi video car wa face book ma' khong duoc la sao' cac ban co cach nao co' the? khac phuc duoc khong Thak!", "answer": "_", "relate_q_q": 0}, {"score": 37.68617, "id": "1154927", "field_search": "question", "question": "Ban cho Minh hoi Minh dien sai thong tin ca nh\u1eafn throng App Store Ben gio vao thi toan tieng Nh\u1ea1c ban khong thoi.gio Minh Pham lam sao", "answer": "_", "relate_q_q": 0}, {"score": 36.79814, "id": "987903", "field_search": "question", "question": "cho minh hoi cai ban oidt minh mua dc 40 ngay gio dem ra ban lai cua hang the gioi di dong co thu lai k", "answer": "_", "relate_q_q": 0}, {"score": 36.730347, "id": "841671", "field_search": "question", "question": " minh muon mua tra gop iphone 6 roi minh ban lai ngay tai cua hang lun co duoc k .neu dc thi lo bao nhieu  ", "answer": "_", "relate_q_q": 0}, {"score": 36.337524, "id": "811422", "field_search": "question", "question": "Quan tri vi\u00ean oi m\u1ecb dang dung dien thoai iPhone 4s phi\u00ean ban 16gb m\u1ecb mu\u00f4\u0301n hoi la ban co the giu\u0301p minh lam the nao de co dk ma pin cua iPhone 4s ko vay", "answer": "_", "relate_q_q": 0}, {"score": 36.275795, "id": "1018530", "field_search": "question", "question": "Ad oi cho hoi Ben Minh co ep mat king may tiny bang ko", "answer": "_", "relate_q_q": 0}, {"score": 35.64788, "id": "905601", "field_search": "question", "question": " Cho minh hoi tao bong bong chat the nao vay ban minh mua may iPhone o thegioididong ", "answer": "_", "relate_q_q": 0}, {"score": 35.168934, "id": "999175", "field_search": "question", "question": "hom qua minh den the gioi di dong de dong tien gop, so tien gop cua minh la 2.638.000d , nhung nhan vien chi thu 2.626.000d minh bi thieu 12k, minh cung ko de y, sang nay minh kiem tra ben tra gop thi ben do van chua nhan duoc tien tra gop cua minh, ban co the kiem tra ho minh ko?", "answer": "_", "relate_q_q": 0}, {"score": 34.829765, "id": "920545", "field_search": "question", "question": " Minh dang sai 4s va phien bang cua minh la 6.1.1 h minh muon up len phien bang i.os 8 duoc kg ban ", "answer": "_", "relate_q_q": 0}, {"score": 34.40843, "id": "1016793", "field_search": "question", "question": "Ad cho minh hoi lam the nao de tat che do an toan vay", "answer": "_", "relate_q_q": 0}, {"score": 33.96294, "id": "854788", "field_search": "question", "question": "AD oi cho minh hoi sao minh xai phan mem minitool roi ma USB cua minh van bi loi ko vao duoc vay AD con cach nao khac chi minh voi!! voi lai o dia cua minh minh duc dia vao thi no cu nhien len dong chu insert disk ma trong kh", "answer": "_", "relate_q_q": 0}, {"score": 33.95301, "id": "1165924", "field_search": "question", "question": "Minh co dua e gui tien cho minh vao so cmnd va so dt tai cua hang, minh da nhan duoc thong bao va ma so nhan tien va minh muon len kiem tra so tien minh hien co va chuyen vao so tk ngan hang cua minh duoc khong ah", "answer": "_", "relate_q_q": 0}, {"score": 33.753246, "id": "902240", "field_search": "question", "question": " Cho hoi em mua iPhone o the gioi Di dong cua MinhMa ben the gioi dd co ho tro Tim Lai iCloud cua Minh ko a ", "answer": "_", "relate_q_q": 0}, {"score": 33.4578, "id": "995537", "field_search": "question", "question": "cho em hoi thanh toan co bang the ATM khong.hay chi dung tien mat", "answer": "_", "relate_q_q": 0}, {"score": 33.385326, "id": "998705", "field_search": "question", "question": "cho minh hoi ben cua hang con bao da trang guong cua may samsung j7 prime ko vay", "answer": "_", "relate_q_q": 0}, {"score": 33.164673, "id": "858592", "field_search": "question", "question": "chao ban, cho minh hoi la man hinh iphone bi bung thi ben TGDD co sua hoac thay man hinh duoc ko ah?Cam on.Phuong Quyen", "answer": "_", "relate_q_q": 0}, {"score": 33.055264, "id": "876240", "field_search": "question", "question": " Cho minh hoi cach tat am thanh khi chup hinh bang iphone? ", "answer": "_", "relate_q_q": 0}, {"score": 32.961693, "id": "1006749", "field_search": "question", "question": "AD oi cho minh hoi ben minh co dien thoai...", "answer": "_", "relate_q_q": 0}, {"score": 32.961514, "id": "1146610", "field_search": "question", "question": "cho minh hoi  may tinh cua minh doi window 7 va no ko the viet chu co dau . Ban co co the chi cach sua loi duoc ko", "answer": "_", "relate_q_q": 0}, {"score": 32.396877, "id": "1002029", "field_search": "question", "question": "alocho minh hoi minh moi mua dien thoai soni chua dc 1 thang, khi mua thi mua lai cua hang tgdd tinh trang moi 90% nhung khi sai thi thay may hay bi lac va cam ung nhay lung tung, jo minh co the doi cai khac k", "answer": "_", "relate_q_q": 0}, {"score": 32.334896, "id": "1160798", "field_search": "question", "question": "cho minh hoi laptop chay cham thi khac phuc nhu the nao", "answer": "_", "relate_q_q": 0}, {"score": 32.11981, "id": "997008", "field_search": "question", "question": "ban oi minh hoi pin moi cua j2prime  bao tien vay ha", "answer": "_", "relate_q_q": 0}, {"score": 32.06068, "id": "824615", "field_search": "question", "question": " cho minh hoi nho minh muon nhan tin bang zalo ma nguoi nhan tin nhan ban sms thi phai lam sao ban ", "answer": "_", "relate_q_q": 0}, {"score": 31.88844, "id": "1003968", "field_search": "question", "question": "cho minh hoi minh mua xiaomi redmi 4x o the gioi di dong ngay 962017 h ben ban thu vao bao nhieu vay", "answer": "_", "relate_q_q": 0}, {"score": 31.853249, "id": "1149130", "field_search": "question", "question": "b oi minh muon mua    ASUS Zenfone Max Pro M1 ben minh con ban ko.?", "answer": "_", "relate_q_q": 0}, {"score": 31.71158, "id": "918094", "field_search": "question", "question": "Ban oi cho minh hoi, truoc gio minh dung itools de chup nhac vao iphone nhung gio itools bat phai mua key, co phan mem nao co the chep nhac tuong tu nhu itools ma fre ko ah?", "answer": "_", "relate_q_q": 0}, {"score": 31.295017, "id": "1166664", "field_search": "question", "question": "Anh oi cho em hoi. Samsung galaxy s10+ ben minh giam 3 trieu. Trong qua tang galaxy app cua em giam duoc them 2 trieu vay minh gop chung duoc phai khong anh . Vay tinh ra la 5 trieu", "answer": "_", "relate_q_q": 0}, {"score": 31.233097, "id": "1154453", "field_search": "question", "question": "cho em hoi em bi dinh loi xac minh tai khoan google ben minh co the sua loi nay duoc khong a", "answer": "_", "relate_q_q": 0}, {"score": 31.156607, "id": "902705", "field_search": "question", "question": "Ban chi minh hoi: zalo cua minh bi dang nhap boi mot may tinh la do minh cho muon may, khi minh cam may thay bao ma QR, vay khi minh dang xuat may tinh tren dien thoai thi may rinh day co dang nhap vao tai khoan cua munh duoc nua ko", "answer": "_", "relate_q_q": 0}, {"score": 31.146606, "id": "1155218", "field_search": "question", "question": "Neu bay gio minh dat mua Samsung A50 128G thi khi nao co hang, minh o Da Nang", "answer": "_", "relate_q_q": 0}, {"score": 30.765503, "id": "997379", "field_search": "question", "question": "Cho em hoi ben minh co dich vu ve sinh dien thoai kg? Chi phi nhu the nao?", "answer": "_", "relate_q_q": 0}, {"score": 30.662664, "id": "939701", "field_search": "question", "question": " cho minh hoi sao dt cua minh zalo ko viet dc tin nhan vay? ban nao biet giup minh voi....thank nhieu ", "answer": "_", "relate_q_q": 0}, {"score": 30.55656, "id": "830874", "field_search": "question", "question": "Cho hoi bay gio tra gop iphone 5s ko can tra truoc dang ap dung tai cua hang nao vay. Toi co CMND va Bang lai xe co tra gop duoc ko.", "answer": "_", "relate_q_q": 0}, {"score": 30.5241, "id": "1161820", "field_search": "question", "question": "Tgdd cho minh hoi minh mua 2 cai dt bang the va tra go\u0301p co \u0111\u01b0\u01a1\u0323c khong", "answer": "_", "relate_q_q": 0}, {"score": 30.434225, "id": "1006088", "field_search": "question", "question": "Minh thanh toan tra gop o tgdd cung duoc 2 thang roi vay minh muon biet la minh co the thanh toan het phan tra gop con lai vao cac thang sau trong mot lan khong khong can phai tra tung thang nua", "answer": "_", "relate_q_q": 0}, {"score": 30.267828, "id": "875419", "field_search": "question", "question": "cho minh hoi minh goi qua messenger sao nguoi ben kia khong nghe thay minh noi. dien thoai cua minh van goi ghi am binh thuong duoc a", "answer": "_", "relate_q_q": 0}, {"score": 30.1575, "id": "1022248", "field_search": "question", "question": "Cho minh hoi iphone ngoai tinh nang chuyen cuoc goi sang so khac thi co tinh nang chuyen tin nhan sang so khac luon duoc khong. Minh dung iphone 6. Neu co thi co the giup minh duoc khong?", "answer": "_", "relate_q_q": 0}, {"score": 30.142859, "id": "835864", "field_search": "question", "question": "Ad oi cho minh hoi minh moi mua may iphone nay nhug kh\u00f4ng biet hang co chinh hang khong. Nho ad tu van dum nhe. Cam on nhieu.", "answer": "_", "relate_q_q": 0}, {"score": 29.954819, "id": "1014524", "field_search": "question", "question": "ad oi e hoi e moi mua cuc sac du phong 300k vao thang 2 gio e muon ban lai ben minh mua hk", "answer": "_", "relate_q_q": 0}, {"score": 29.953049, "id": "835010", "field_search": "question", "question": " cho minh hoi,neu minh mua dt iphone 5s tra gop truoc 0d,thi hang minh phai dong bao nhieu trong 1 nam ", "answer": "_", "relate_q_q": 0}, {"score": 29.945126, "id": "1148416", "field_search": "question", "question": "cho e hoi la iphone cua e sau khi reset thi no bi loi khong nhan sim thi phai lam the nao a?", "answer": "_", "relate_q_q": 0}, {"score": 29.835306, "id": "830150", "field_search": "question", "question": "lam on cho minh hoico chiec iphon4 ma minh vao itunes de khoi phuc lai tu dau ma bay gio may doi hoi ID apple ma minh khong biet tai khoan cu cua may thi lam the nao", "answer": "_", "relate_q_q": 0}, {"score": 29.8073, "id": "998556", "field_search": "question", "question": "em muon tat che do an toan cua may samsung j7 prime thi lam the nao", "answer": "_", "relate_q_q": 0}, {"score": 29.736343, "id": "1003953", "field_search": "question", "question": "cho e hoi ben minh co khoi phuc duoc du lieu da bi mat tren the SD khong a", "answer": "_", "relate_q_q": 0}, {"score": 29.57523, "id": "1020006", "field_search": "question", "question": "Cho minh ho. Minh moi mua Dien thoai sony xa1 untral tai the gioi di dong .bay gio minh muon doi cai khac .thi ben the gioi di dong cho doi cai samsung j7 pro  thi la bao nhieu .may mua duoc co 4ngay roi .xin cho minh thong tin .cam on", "answer": "_", "relate_q_q": 0}, {"score": 29.475113, "id": "1021995", "field_search": "question", "question": "minh co mua dt zenphone 2 tai thegioididong minh tinh ban lai cho cua hang co dc ko ad???", "answer": "_", "relate_q_q": 0}, {"score": 29.435896, "id": "900981", "field_search": "question", "question": "cho m\u00ecnh h\u1ecfi tai sao Ipad 2 cua minh \u00e0o kho\u1ea3ng 2 tu\u1ea7n thi am thanh thoi bi re rat kho ngen den sang nay th\u00ec loa ko phat ti\u1ebfng n\u1eefa m\u00e0 khi ngan tai nghe vao thi co ti\u1ebfng cho m\u00ecnh hoi co phai loa", "answer": "_", "relate_q_q": 0}, {"score": 29.399708, "id": "848725", "field_search": "question", "question": "Cty cho minh hoi . Minh mua iPhone 5s moi sai duoc gan 2 thang . Gio minh mu\u00f4\u0301n ban di thi TGDD co thu lai ko. May minh mua tai TGDD lun . Va mat bao nhi\u00ea\u0300u Phan tram", "answer": "_", "relate_q_q": 0}, {"score": 29.357355, "id": "1010971", "field_search": "question", "question": "Cho e hoi tai sao bat Unikey len thi khong xai duoc va hien len man hinh cai bang nay??Va phai khac phuc nhu the nao?", "answer": "_", "relate_q_q": 0}, {"score": 29.263826, "id": "989295", "field_search": "question", "question": "ban oi cho m hoi ti nheiphine 5 cua minh sao danh dung doi khi keu chuong canh baoluc do m check thi ko co thong bao hay tin nhan gi ca, la sao", "answer": "_", "relate_q_q": 0}, {"score": 28.911808, "id": "997212", "field_search": "question", "question": "cho minh hoi minh mua may s7 ed o the gioi di dong duoc 6th.minh mun ban lai vay the gioi di dong thu lai dc bao nhieu ahmay con nguyen ven", "answer": "_", "relate_q_q": 0}, {"score": 28.818323, "id": "868471", "field_search": "question", "question": "Ad cho minh hoi. Do cong viec nen minh di thuong xuyen. Nen minh toan sac iphone minh bang sac du phong. Dieu nay co anh huong gi toi may hay pin ko.", "answer": "_", "relate_q_q": 0}, {"score": 28.771809, "id": "1013559", "field_search": "question", "question": "Cho minh hoi may Q edgy nen dung phien ban ch play nao vA phien ban dich vu play nao...neu co thi gui link cho mik nha", "answer": "_", "relate_q_q": 0}, {"score": 28.732601, "id": "1006110", "field_search": "question", "question": "Xin hoi minh muon sao luu dat lai may sam sung ri5.minh quen mat khau thi phai lam nhu the nao.", "answer": "_", "relate_q_q": 0}, {"score": 28.709297, "id": "997238", "field_search": "question", "question": "Cho minh hoi Google oh man h\u00ecnh chinh bi mat thi l\u00e0 the nao de lay lai dc", "answer": "_", "relate_q_q": 0}, {"score": 28.456142, "id": "992552", "field_search": "question", "question": "Cho minh hoi may iphone5 ko co sim co the dung zalo dc ko ban?vi minh thay may cua ban minh co thong bao zalo nhung ban minh bao ko truy cap dc vi minh mua lai cua nguoi ta!nhung tin nhan zalo van gui den,co thong bao luon!hay ban minh cai dat phan mem gi", "answer": "_", "relate_q_q": 0}, {"score": 28.391794, "id": "1150569", "field_search": "question", "question": "bn oi  cho minh hoi la may cua minh no bao ve la dich vu google play lien tuc dung la bai sao vay ban j3 pro", "answer": "_", "relate_q_q": 0}, {"score": 28.350054, "id": "1159624", "field_search": "question", "question": "Cho hoi minh m\u1edbi mua m\u00e1y coolpad m\u00e0 mua loai hang c\u0169 o the gioi di dong.cho hoi vay minh xai duoc khoang 10ngay.m\u00e1y v\u00e2n binh thuong.c\u00f2n hop va phu kien.vay thu lai mat phi bao nhiu vay", "answer": "_", "relate_q_q": 0}, {"score": 28.27069, "id": "1151659", "field_search": "question", "question": "Livestream tren fb bang m20 the nao ad? Minh kiem hoai ko thay", "answer": "_", "relate_q_q": 0}, {"score": 28.209093, "id": "1004652", "field_search": "question", "question": "Cho minh hoi ben ban con man hinh may htc m8 khong minh qua thay. Cam on", "answer": "_", "relate_q_q": 0}, {"score": 28.177227, "id": "840467", "field_search": "question", "question": "Ban oi co cach nao mo duoc tin nhan facebook khi mo trinh suyen internet hay chrom k? No lien ket voi messenger k mo dc ban ah. Mih k mun su dung mesenger. Ban co cach nao giup minh voi.", "answer": "_", "relate_q_q": 0}, {"score": 28.137007, "id": "1136677", "field_search": "question", "question": "ban oi cho minh hoi con m\u00e1y sam sunggalasy A6 kh\u00f4ng", "answer": "_", "relate_q_q": 0}, {"score": 28.020218, "id": "1010940", "field_search": "question", "question": "Chi em hoi Minh muon xem bao hanh phu kien minh phai lam sao ak    khi khong ra cua hang", "answer": "_", "relate_q_q": 0}, {"score": 27.956633, "id": "1139100", "field_search": "question", "question": "cho mk hoi con iphon 8 plus mau red ko con ban a ,minh muon tim mua ma ko the nao tim dc", "answer": "_", "relate_q_q": 0}, {"score": 27.903254, "id": "1135277", "field_search": "question", "question": "cho e hoi ben minh co ban speaker laptop TP500L ko vay", "answer": "_", "relate_q_q": 0}, {"score": 27.893312, "id": "841039", "field_search": "question", "question": "Admin \u01a0i iPad 4 nang cap Len phien ban 9.3.2 ha xuong 9.2.1 duoc Kh\u00f4ng admin. Neu duoc Minh co the mang qua Ben the gioi di dong de ha cap duoc Kh\u00f4ng admin", "answer": "_", "relate_q_q": 0}, {"score": 27.817894, "id": "1150178", "field_search": "question", "question": "da cho e hoi muon bo dia dvd vao laptop idepad 330 de xem phim thi minh lam the nao", "answer": "_", "relate_q_q": 0}, {"score": 27.756649, "id": "1005479", "field_search": "question", "question": "cho a hoi ben minh co ban pin laptop levono G480 khong vay?", "answer": "_", "relate_q_q": 0}, {"score": 27.749207, "id": "1020005", "field_search": "question", "question": "minh vua mua lap top nhung khi mo wold voi ex  thi may tinh hien doi mua. khong biet khi mua co duoc tang kem theo khong nhi?", "answer": "_", "relate_q_q": 0}, {"score": 27.671507, "id": "1167669", "field_search": "question", "question": "cho hoi...hien tai minh moi mua san pham oppo f11...qua thoi gian su dung duoc 1 tuan...minh cai hinh anh tu dien thoai khac ve dien thoai oppo nhung hom nay da bi mat het hinh anh va choi game dung luong thap nhung hay bi dung man hinh....cho hoi vay co the den cua hang doi lai dien thoai duoc hay khong...minh moi mua duoc 1 tuan...", "answer": "_", "relate_q_q": 0}, {"score": 27.481636, "id": "1152653", "field_search": "question", "question": "Cac ban cho minh hoi la lam the nao de dung  Fake GPS Location  Ho la cho may ximao note 6pro?", "answer": "_", "relate_q_q": 0}, {"score": 27.437826, "id": "920493", "field_search": "question", "question": "\u0110\u1ee3t tr\u01b0\u1edbc minh co mua 1 cai laptop hp o thegioididong sau do phat hien may bi loi diem chet va duoc doi 1 cai may moi. nhung dao gan day dem len hang bao hanh thi duoc biet may nay duoc mua boi mot nguoi khac ten thuy sdt khac cua minh.. o hang con bao may bi vao nuoc, am IC trong khi may minh chi sd xem phim buoi toi khoang tam 1 - 2 tieng/ngay va minh khang dinh chua bao gio de nuoc vao may. co khi nao thegioididong dem hang doi tra ban cho khach khong? minh tin tuong o day nen mua 1 laptop 3 em dien thoai. nhung sau vu nay chac nghi choi qua. mong thegioididong.com cho minh mot loi giai thich ro rang nhe,cam on.", "answer": "_", "relate_q_q": 0}, {"score": 27.398615, "id": "1001558", "field_search": "question", "question": "ad cho em hoi cai em co mua 1 cai card gate fpt tgdd h em nap vao card vao the ngan hang cua em co dc ko a", "answer": "_", "relate_q_q": 0}, {"score": 27.397285, "id": "922120", "field_search": "question", "question": " ban cho minh hoi minh quen mat khau chu cho may tinh bang lenovo 3500 bay gio lam sao .cam on ", "answer": "_", "relate_q_q": 0}, {"score": 27.378036, "id": "871069", "field_search": "question", "question": " cho minh hoi iphone nong qua co the de vao tu lanh duoc khong ", "answer": "_", "relate_q_q": 0}, {"score": 27.299948, "id": "805412", "field_search": "question", "question": " Anh chi cho e hoi cach nap the mua hang tren appstore nhu the nao v\u1eady ", "answer": "_", "relate_q_q": 0}, {"score": 27.268616, "id": "1009004", "field_search": "question", "question": "Muon tai video tren web ve iphone minh lam nhu the nao vay ban", "answer": "_", "relate_q_q": 0}, {"score": 27.091614, "id": "1016779", "field_search": "question", "question": "Cho minh hoi minh bat che do tim iphone no co hien thi ky hieu nao tren chiec iphone do ko", "answer": "_", "relate_q_q": 0}, {"score": 27.00191, "id": "987220", "field_search": "question", "question": "HI AD MINH CO CAI J5 2016 MUON DOI MAY MOI THEO CHUONG TRINH CUA CONG TY THI LAM NHU THE NAO", "answer": "_", "relate_q_q": 0}, {"score": 26.861338, "id": "1012933", "field_search": "question", "question": "anh chi ben the gioi di dong oi cho em hoi bay gio em muon quy doi gia chi cua chiec may cua  em gui di bao hanh sang mot san pham tuong duong gia tri cua chiec may do co duoc khong vay", "answer": "_", "relate_q_q": 0}, {"score": 26.64815, "id": "1145066", "field_search": "question", "question": "Minh mua mua active 1 minh tra g\u00f3p bang the sacombank d\u01b0\u1ee3c khong", "answer": "_", "relate_q_q": 0}, {"score": 26.5495, "id": "1147755", "field_search": "question", "question": "tai sao minh khong the xem duoc trang ca nhan cua minh va moi nguoi khi dang nhap tren laptop a?", "answer": "_", "relate_q_q": 0}, {"score": 26.498398, "id": "995510", "field_search": "question", "question": "Vui long cho hoi  Phieu mua hang co the mua duoc nhung gi ?", "answer": "_", "relate_q_q": 0}, {"score": 26.49733, "id": "1004841", "field_search": "question", "question": "Ad cho hoi nha e o xa thieu ly huyen thieu hoa tinh thanh hoa, em can mua 5 the 500k vt ,ben minh co giao hag tan nha ko?", "answer": "_", "relate_q_q": 0}, {"score": 26.48976, "id": "1161517", "field_search": "question", "question": "Ban oi cho minh hoi dt s\u00e1mung j6 minh xai dc khoan 3 thang bn thu lai bao nhju a", "answer": "_", "relate_q_q": 0}, {"score": 26.442337, "id": "1007958", "field_search": "question", "question": "Cho minh hoi minh co mua may tai tgdd bay gio minh ko muon sai nua muon ban de mua dien thoai khac vay ben tgdd co mua lai may ko vay...", "answer": "_", "relate_q_q": 0}, {"score": 26.298313, "id": "1145027", "field_search": "question", "question": "may tinh cua minh asus khong dung duoc hang phim so chinh. cach khac phuc ntn vay? minh cam on", "answer": "_", "relate_q_q": 0}, {"score": 26.176252, "id": "995728", "field_search": "question", "question": "Cho minh hoi hom qua minh mua nham o tgdd mot  The gate bay gio minh muon doi sang tjen mat duoc ko .minh chiu mat phi", "answer": "_", "relate_q_q": 0}, {"score": 26.028204, "id": "832433", "field_search": "question", "question": "minh bi mot tai khoan zalo chan mot thoi gian, minh cung da xoa tai khoan do trong danh ba zalo cua minh nhung k hieu sao gan day zalo goi cho minh \" tai khoan chan minh dang su dung zalo ban hay de lai loi chao de tro chuyen\" the nay la the nao?", "answer": "_", "relate_q_q": 0}, {"score": 25.95868, "id": "1143088", "field_search": "question", "question": "Cho minh hoi galaxy s8 bay gio la bao nhieu ? Va ben the gioi didong co thu mua lai khong ?", "answer": "_", "relate_q_q": 0}, {"score": 25.88777, "id": "996113", "field_search": "question", "question": "Cho hoi la minh dang tra gop a7 2017 thi c\u00f3 duoc l\u00ean the gioi di dong doi qua may galaxy j7 pro ko", "answer": "_", "relate_q_q": 0}, {"score": 25.845087, "id": "816261", "field_search": "question", "question": "Minh muon cai dat ID app mien phi de dang ky iTunes & App Store. Vi dang ky tai khoan moi tren may doi thanh toan qua visa, con neu tai app mien phi thi kg co tk sao tai ve duoc ban", "answer": "_", "relate_q_q": 0}, {"score": 25.81699, "id": "1010903", "field_search": "question", "question": "cho hoi  day sat  Minh  mua  o cua hang lau r\u1ed3i  xai  1thoi  gian Bi  l\u00f2ng  kia doi  di HK c\u1eeda  hang  keu  bao  Hanh  1nam", "answer": "_", "relate_q_q": 0}, {"score": 25.804676, "id": "996507", "field_search": "question", "question": "Minh co vay ben vpbank bi no xau,nhung minh tra xong het roi,muon hoi xem co mua dt tra gop duoc hk", "answer": "_", "relate_q_q": 0}, {"score": 25.746393, "id": "1146592", "field_search": "question", "question": "Ban co the cho minh xem mot vai mau op lung galaxy j4 core duoc khong", "answer": "_", "relate_q_q": 0}, {"score": 25.643171, "id": "843693", "field_search": "question", "question": " Cho minh hoi dt iphone 4s minh co pai chinh hang ko. IME 013065004667760 ", "answer": "_", "relate_q_q": 0}, {"score": 25.605452, "id": "824553", "field_search": "question", "question": "Ad cho minh hoi id apple cua minh bi vo hieu hoa bay gio phai lam gi cung nhu cap nhat game ho\u0103\u0323c YouTube thi may bao id apple cua ban bi vo hieu hoa do bao mat thi phai lam sao?", "answer": "_", "relate_q_q": 0}, {"score": 25.544195, "id": "947239", "field_search": "question", "question": "  CHAO BAN CHO MINH HOI MAY NAY LA MAY IP CUA MY BAN QUOC TE PAI KO BAN ", "answer": "_", "relate_q_q": 0}]}